mvp-0/modules/alu.v
module alu(
    input wire [31:0] A, B,
    input wire [2:0] func3,
    input wire [6:0] func7,
    input wire [4:0] shamt,

    input wire isALUreg,
    input wire isALUimm,
    input wire isBranch,
    input wire isJALR,
    input wire isJAL,
    input wire isAUIPC,
    input wire isLUI,
    input wire isLoad,
    input wire isStore,

    output reg EQ, EQM, EQM_U,
    output reg [31:0] Q

    
);

always @(*) 
begin
        Q = 32'b0;

        if (isALUreg || isALUimm) 
        begin
            case (func3)
                3'b000: 
                begin
                    if (func7[5] && isALUreg)
                        Q = A - B;
                    else 
                        Q = A + B;
                end
                3'b111: Q = A & B;
                3'b110: Q = A | B;
                3'b100: Q = A ^ B;
                3'b001: Q = A << shamt;
                3'b101: Q = (func7[5]) ? (A >>> shamt) : (A >> shamt);
                3'b010: Q = ($signed(A) < $signed(B)) ? 32'b1 : 32'b0;
                3'b011: Q = (A < B) ? 32'b1 : 32'b0;
                default: Q = 32'b0;
            endcase
        end
        else if (isAUIPC) 
        begin
            Q = A + B;
        end
        else if (isLUI) 
        begin
            Q = B;
        end
        else if (isJAL || isJALR) 
        begin
            Q = A + 4;
        end
        else if (isLoad || isStore) 
        begin
            Q = A + B;
        end
        else 
        begin
            Q = 32'b0;
        end
    end

endmodule

mvp-0/modules/sim/alu/tb_alu.v
`timescale 1ns/1ps

module tb_alu;
    reg [31:0] A, B;
    reg [2:0] func3;
    reg [6:0] func7;
    reg [4:0] shamt;
    
    reg isALUreg;
    reg isALUimm;
    reg isBranch;
    reg isJALR;
    reg isJAL;
    reg isAUIPC;
    reg isLUI;
    reg isLoad;
    reg isStore;

    wire EQ, EQM, EQM_U;
    wire [31:0] Q;

    alu dut(
        .A(A),
        .B(B),
        .func3(func3),
        .func7(func7),
        .shamt(shamt),
        .isALUreg(isALUreg),
        .isALUimm(isALUimm),
        .isBranch(isBranch),
        .isJALR(isJALR),
        .isJAL(isJAL),
        .isAUIPC(isAUIPC),
        .isLUI(isLUI),
        .isLoad(isLoad),
        .isStore(isStore),
        .EQ(EQ),
        .EQM(EQM),
        .EQM_U(EQM_U),
        .Q(Q)
    );

    initial begin
        $dumpfile("tb_alu.vcd");
        $dumpvars(0, tb_alu);

        isALUreg = 0; 
        isALUimm = 0; 
        isBranch = 0; 
        isJALR = 0; 
        isJAL = 0;
        isAUIPC = 0; 
        isLUI = 0; 
        isLoad = 0; 
        isStore = 0;

        // Test 1: ADD (func3 = 000, func7 = 0000000)
        A = 32'h00000001;
        B = 32'h00000002;
        func3 = 3'b000;
        func7 = 7'b0000000;
        shamt = 0;
        isALUreg = 1;
        #10;
        $display("ADD -> A = %h, B = %h, Q = %h", A, B, Q);

        // Test 2: SUB (func3 = 000, func7 = 0100000)
        func7 = 7'b0100000;
        #10;
        $display("SUB -> A = %h, B = %h, Q = %h", A, B, Q);

        // Test 3: AND (func3 = 111)
        func3 = 3'b111;
        func7 = 7'b0000000;
        #10;
        $display("AND -> A = %h, B = %h, Q = %h", A, B, Q);

        // Test 4: OR (func3 = 110)
        func3 = 3'b110;
        #10;
        $display("OR -> A = %h, B = %h, Q = %h", A, B, Q);

        // Test 5: XOR (func3 = 100)
        func3 = 3'b100;
        #10;
        $display("XOR -> A = %h, B = %h, Q = %h", A, B, Q);

        // Test 6: SLL (func3 = 001)
        func3 = 3'b001;
        shamt = 5'd1;
        #10;
        $display("SLL -> A = %h, shamt = %d, Q = %h", A, shamt, Q);

        // Test 7: SRL (func3 = 101, func7 = 0000000)
        func3 = 3'b101;
        func7 = 7'b0000000;
        #10;
        $display("SRL -> A = %h, shamt = %d, Q = %h", A, shamt, Q);

        // Test 8: SRA (func3 = 101, func7 = 0100000)
        func7 = 7'b0100000;
        A = 32'hFFFFFFF0;  // valor negativo
        #10;
        $display("SRA -> A = %h, shamt = %d, Q = %h", A, shamt, Q);

        // Test 9: SLT (signed comparison)
        func3 = 3'b010;
        func7 = 7'b0000000;
        A = -5;
        B = 3;
        #10;
        $display("SLT -> A = %h, B = %h, Q = %h", A, B, Q);

        // Test 10: SLTU (unsigned comparison)
        func3 = 3'b011;
        A = 2;
        B = 3;
        #10;
        $display("SLTU -> A = %h, B = %h, Q = %h", A, B, Q);

        $finish;
    end
endmodule

mvp-0/modules/sim/alu/tb_alu.vcd
$date
	Sun May 04 23:08:27 2025
$end
$version
	Icarus Verilog
$end
$timescale
	1ps
$end
$scope module tb_alu $end
$var wire 32 ! Q [31:0] $end
$var wire 1 " EQM_U $end
$var wire 1 # EQM $end
$var wire 1 $ EQ $end
$var reg 32 % A [31:0] $end
$var reg 32 & B [31:0] $end
$var reg 3 ' func3 [2:0] $end
$var reg 7 ( func7 [6:0] $end
$var reg 1 ) isALUimm $end
$var reg 1 * isALUreg $end
$var reg 1 + isAUIPC $end
$var reg 1 , isBranch $end
$var reg 1 - isJAL $end
$var reg 1 . isJALR $end
$var reg 1 / isLUI $end
$var reg 1 0 isLoad $end
$var reg 1 1 isStore $end
$var reg 5 2 shamt [4:0] $end
$scope module dut $end
$var wire 32 3 A [31:0] $end
$var wire 32 4 B [31:0] $end
$var wire 3 5 func3 [2:0] $end
$var wire 7 6 func7 [6:0] $end
$var wire 1 ) isALUimm $end
$var wire 1 * isALUreg $end
$var wire 1 + isAUIPC $end
$var wire 1 , isBranch $end
$var wire 1 - isJAL $end
$var wire 1 . isJALR $end
$var wire 1 / isLUI $end
$var wire 1 0 isLoad $end
$var wire 1 1 isStore $end
$var wire 5 7 shamt [4:0] $end
$var reg 1 $ EQ $end
$var reg 1 # EQM $end
$var reg 1 " EQM_U $end
$var reg 32 8 Q [31:0] $end
$upscope $end
$upscope $end
$enddefinitions $end
#0
$dumpvars
b11 8
b0 7
b0 6
b0 5
b10 4
b1 3
b0 2
01
00
0/
0.
0-
0,
0+
1*
0)
b0 (
b0 '
b10 &
b1 %
x$
x#
x"
b11 !
$end
#10000
b11111111111111111111111111111111 !
b11111111111111111111111111111111 8
b100000 (
b100000 6
#20000
b0 !
b0 8
b0 (
b0 6
b111 '
b111 5
#30000
b11 !
b11 8
b110 '
b110 5
#40000
b11 !
b11 8
b100 '
b100 5
#50000
b10 !
b10 8
b1 2
b1 7
b1 '
b1 5
#60000
b0 !
b0 8
b101 '
b101 5
#70000
b1111111111111111111111111111000 !
b1111111111111111111111111111000 8
b11111111111111111111111111110000 %
b11111111111111111111111111110000 3
b100000 (
b100000 6
#80000
b1 !
b1 8
b11 &
b11 4
b11111111111111111111111111111011 %
b11111111111111111111111111111011 3
b0 (
b0 6
b10 '
b10 5
#90000
b1 !
b1 8
b10 %
b10 3
b11 '
b11 5
