mvp-0/modules/alu.v
module alu(
    input wire [31:0] A, B,
    input wire [2:0] func3,
    input wire [6:0] func7,
    input wire [6:0] opcode,
    input wire [4:0] shamt,
    output reg EQ, EQM, EQM_U,
    output reg [31:0] Q
);

always @(*) 
begin
    case(opcode)
    /* Immediate Instructions and Record Upload */
        7'b0110111: //LUI
            Q = B;
        7'b0010111: //AUIPC
            Q = A + B;
        7'b1101111: //JAL
            Q = 0;
        7'b1100111: //JALR
            Q = A + B;

        /* Jumping Instructions */
        7'b1100011: //JUMP
            case(func3)
                3'b000: //BEQ
                    Q = A == B;
                3'b001: //BNQ
                    Q = A != B;
                3'b100: //BLT
                    Q = $signed(A) < $signed(B);
                3'b101: //BGE
                    Q = $signed(A) >= $signed(B);
                3'b110: //BLTU
                    Q = A < B;
                default: //BGEU
                    Q = A >= B;
            endcase

        /* Load and Store Instructions */
        7'b0000011:     //LOAD
            Q = A + B;

        7'b0100011:     //STORE
            Q = A + B;

        /* Immediate Instructions */
        7'b0010011:
            case(func3)
                3'b000: //ADDI
                    Q = A + B;
                3'b010: //SLTI, Q = 1 if A<B
                    Q = $signed(A) < $signed(B);
                3'b011: //SLTI Unsigned, Q = 1 if A<B
                    Q = A < B;
                3'b100: //XORI
                    Q = A ^ B;
                3'b110: //ORI
                    Q = A | B;
                3'b111: //ANDI
                    Q = A & B;
                3'b001: //SHIFT LEFT LOGICAL IMMEDIATE (SLLI)
                    Q = A << shamt;
                default:
                    Q = (func7[5]) ? (A >>> shamt) : (A >> shamt); //SRA or SRL
            endcase

        /* Operations */
        7'b0110011:
            case(func3)
                3'b000:
                    Q = (func7[5]) ? (A - B) : (A + B); //SUB or ADD
                3'b010: //SLT, Q = 1 if A<B
                    Q = A < B;
                3'b011: //SLT Unsigned, Q = 1 if A<B
                    Q = $signed(A) < $signed(B);
                3'b100: //XOR
                    Q = A ^ B;
                3'b001: //SHIFT LEFT LOGICAL
                    Q = A << shamt;
                3'b101:
                    Q = (func7[5]) ? (A >>> shamt) : (A >> shamt); //SRA or SRL
                3'b110: //OR
                    Q = A | B;
                default: //AND
                    Q = A & B;
            endcase
        default: //NOP
            Q = 0;
    endcase

    EQ = A == B;
    EQM = A > B;
    EQM_U = A < B;
end
endmodule

mvp-0/modules/sim/alu/tb_alu.v
`timescale 1ns/1ps

module tb_alu;
    reg [31:0] A, B;
    reg [2:0] func3;
    reg [6:0] func7;
    reg [6:0] opcode;
    reg [4:0] shamt;

    wire EQ, EQM, EQM_U;
    wire [31:0] Q;

    alu dut(
        .A(A),
        .B(B),
        .func3(func3),
        .func7(func7),
        .opcode(opcode),
        .shamt(shamt),
        .EQ(EQ),
        .EQM(EQM),
        .EQM_U(EQM_U),
        .Q(Q)
    );

    initial begin
        $dumpfile("tb_alu.vcd");
        $dumpvars(0, tb_alu);

        // Test 1: ADD (opcode = 0110011, func3 = 000, func7 = 0000000)
        A = 32'h00000001;
        B = 32'h00000002;
        opcode = 7'b0110011;
        func3 = 3'b000;
        func7 = 7'b0000000;
        #10;
        $display("Test 1: ADD (opcode = 0110011, func3 = 000, func7 = 0000000)");
        $display("Time %0t: ADD -> A = %h, B = %h, Q = %h", $time, A, B, Q);

        #10;

        // Test 2: SUB (opcode = 0110011, func3 = 000, func7 = 0100000)
        func7 = 7'b0100000;
        #10;
        $display("Test 2: SUB (opcode = 0110011, func3 = 000, func7 = 0100000)");
        $display("Time %0t: SUB -> A = %h, B = %h, Q = %h", $time, A, B, Q);

        #10;

        // Test 3: AND (opcode = 0110011, func3 = 111, func7 = 0000000)
        func3 = 3'b111;
        func7 = 7'b0000000;
        #10;
        $display("Test 3: AND (opcode = 0110011, func3 = 111, func7 = 0000000)");
        $display("Time %0t: AND -> A = %h, B = %h, Q = %h", $time, A, B, Q);

        #10;

        // Test 4: OR (opcode = 0110011, func3 = 110, func7 = 0000000)
        func3 = 3'b110;
        #10;
        $display("Test 4: OR (opcode = 0110011, func3 = 110, func7 = 0000000)");
        $display("Time %0t: OR -> A = %h, B = %h, Q = %h", $time, A, B, Q);

        #10;

        // Test 5: XOR (opcode = 0110011, func3 = 100, func7 = 0000000)
        func3 = 3'b100;
        #10;
        $display("Test 5: XOR (opcode = 0110011, func3 = 100, func7 = 0000000)");
        $display("Time %0t: XOR -> A = %h, B = %h, Q = %h", $time, A, B, Q);

        #10;

        // Test 6: SLL (opcode = 0110011, func3 = 001, func7 = 0000000)
        func3 = 3'b001;
        shamt = 5'b00001;
        #10;
        $display("Test 6: SLL (opcode = 0110011, func3 = 001, func7 = 0000000)");
        $display("Time %0t: SLL -> A = %h, B = %h, Q = %h", $time, A, B, Q);

        #10;

        // Test 7: SRL (opcode = 0110011, func3 = 101, func7 = 0000000)
        func3 = 3'b101;
        #10;
        $display("Test 7: SRL (opcode = 0110011, func3 = 101, func7 = 0000000)");
        $display("Time %0t: SRL -> A = %h, B = %h, Q = %h", $time, A, B, Q);

        #10;

        // Test 8: SRA (opcode = 0110011, func3 = 101, func7 = 0100000)
        func7 = 7'b0100000;
        #10;
        $display("Test 8: SRA (opcode = 0110011, func3 = 101, func7 = 0100000)");
        $display("Time %0t: SRA -> A = %h, B = %h, Q = %h", $time, A, B, Q);

        #10;

        // Test 9: SLT (opcode = 0110011, func3 = 010, func7 = 0000000)
        func3 = 3'b010;
        A = -7;
        B = 6;
        #10;
        $display("Test 9: SLT (opcode = 0110011, func3 = 010, func7 = 0000000)");
        $display("Time %0t: SLT -> A = %h, B = %h, Q = %h", $time, A, B, Q);

        #10;

        // Test 10: SLTU (opcode = 0110011, func3 = 011, func7 = 0000000)
        func3 = 3'b011;
        A = 2;
        B = 3;
        #10;
        $display("Test 10: SLTU (opcode = 0110011, func3 = 011, func7 = 0000000)");
        $display("Time %0t: SLTU -> A = %h, B = %h, Q = %h", $time, A, B, Q);

        #10;

        $finish;
    end
endmodule

mvp-0/modules/sim/alu/tb_alu.vcd
$date
	Thu Mar 27 10:42:58 2025
$end
$version
	Icarus Verilog
$end
$timescale
	1ps
$end
$scope module tb_alu $end
$var wire 32 ! Q [31:0] $end
$var wire 1 " EQM_U $end
$var wire 1 # EQM $end
$var wire 1 $ EQ $end
$var reg 32 % A [31:0] $end
$var reg 32 & B [31:0] $end
$var reg 3 ' func3 [2:0] $end
$var reg 7 ( func7 [6:0] $end
$var reg 7 ) opcode [6:0] $end
$var reg 5 * shamt [4:0] $end
$scope module dut $end
$var wire 32 + A [31:0] $end
$var wire 32 , B [31:0] $end
$var wire 3 - func3 [2:0] $end
$var wire 7 . func7 [6:0] $end
$var wire 7 / opcode [6:0] $end
$var wire 5 0 shamt [4:0] $end
$var reg 1 $ EQ $end
$var reg 1 # EQM $end
$var reg 1 " EQM_U $end
$var reg 32 1 Q [31:0] $end
$upscope $end
$upscope $end
$enddefinitions $end
$comment Show the parameter values. $end
$dumpall
$end
#0
$dumpvars
b11 1
bx 0
b110011 /
b0 .
b0 -
b10 ,
b1 +
bx *
b110011 )
b0 (
b0 '
b10 &
b1 %
0$
0#
1"
b11 !
$end
#20000
b11111111111111111111111111111111 !
b11111111111111111111111111111111 1
b100000 (
b100000 .
#40000
b0 !
b0 1
b0 (
b0 .
b111 '
b111 -
#60000
b11 !
b11 1
b110 '
b110 -
#80000
b100 '
b100 -
#100000
b10 !
b10 1
b1 *
b1 0
b1 '
b1 -
#120000
b0 !
b0 1
b101 '
b101 -
#140000
b100000 (
b100000 .
#160000
0"
1#
b110 &
b110 ,
b11111111111111111111111111111001 %
b11111111111111111111111111111001 +
b10 '
b10 -
#180000
1"
0#
b1 !
b1 1
b11 &
b11 ,
b10 %
b10 +
b11 '
b11 -
